LICENSE
MANIFEST.in
readme.md
requirements.txt
setup.py
lingua_nostra/__init__.py
lingua_nostra/bracket_expansion.py
lingua_nostra/config.py
lingua_nostra/format.py
lingua_nostra/internal.py
lingua_nostra/parse.py
lingua_nostra/time.py
lingua_nostra.egg-info/PKG-INFO
lingua_nostra.egg-info/SOURCES.txt
lingua_nostra.egg-info/dependency_links.txt
lingua_nostra.egg-info/requires.txt
lingua_nostra.egg-info/top_level.txt
lingua_nostra/lang/__init__.py
lingua_nostra/lang/common_data_ca.py
lingua_nostra/lang/common_data_cs.py
lingua_nostra/lang/common_data_da.py
lingua_nostra/lang/common_data_de.py
lingua_nostra/lang/common_data_en.py
lingua_nostra/lang/common_data_es.py
lingua_nostra/lang/common_data_fa.py
lingua_nostra/lang/common_data_fr.py
lingua_nostra/lang/common_data_hu.py
lingua_nostra/lang/common_data_it.py
lingua_nostra/lang/common_data_nl.py
lingua_nostra/lang/common_data_pl.py
lingua_nostra/lang/common_data_pt.py
lingua_nostra/lang/common_data_sl.py
lingua_nostra/lang/common_data_sv.py
lingua_nostra/lang/format_ca.py
lingua_nostra/lang/format_common.py
lingua_nostra/lang/format_cs.py
lingua_nostra/lang/format_da.py
lingua_nostra/lang/format_de.py
lingua_nostra/lang/format_en.py
lingua_nostra/lang/format_es.py
lingua_nostra/lang/format_fa.py
lingua_nostra/lang/format_fr.py
lingua_nostra/lang/format_hu.py
lingua_nostra/lang/format_it.py
lingua_nostra/lang/format_nl.py
lingua_nostra/lang/format_pl.py
lingua_nostra/lang/format_pt.py
lingua_nostra/lang/format_sl.py
lingua_nostra/lang/format_sv.py
lingua_nostra/lang/parse_ca.py
lingua_nostra/lang/parse_common.py
lingua_nostra/lang/parse_cs.py
lingua_nostra/lang/parse_da.py
lingua_nostra/lang/parse_de.py
lingua_nostra/lang/parse_en.py
lingua_nostra/lang/parse_es.py
lingua_nostra/lang/parse_fa.py
lingua_nostra/lang/parse_fr.py
lingua_nostra/lang/parse_hu.py
lingua_nostra/lang/parse_it.py
lingua_nostra/lang/parse_nl.py
lingua_nostra/lang/parse_pl.py
lingua_nostra/lang/parse_pt.py
lingua_nostra/lang/parse_sl.py
lingua_nostra/lang/parse_sv.py
lingua_nostra/res/text/ca-es/and.word
lingua_nostra/res/text/ca-es/date_time.json
lingua_nostra/res/text/ca-es/date_time_test.json
