Metadata-Version: 2.1
Name: lingua-nostra
Version: 0.4.5
Summary: Lingua_Nostra is chatterbox's natural language parser, it converts natural language into data structures, and data structures into natural language!
Home-page: https://github.com/HelloChatterbox/lingua-nostra
License: Apache2.0
Platform: UNKNOWN
Classifier: Development Status :: 4 - Beta
Classifier: Intended Audience :: Developers
Classifier: Topic :: Text Processing :: Linguistic
Classifier: License :: OSI Approved :: Apache Software License
Classifier: Programming Language :: Python :: 3.6
Classifier: Programming Language :: Python :: 3.7
Classifier: Programming Language :: Python :: 3.8
Classifier: Programming Language :: Python :: 3.9
License-File: LICENSE
